pyasyncbtrack/__init__.py
pyasyncbtrack/agent.py
pyasyncbtrack/consistency.py
pyasyncbtrack/constraints.py
pyasyncbtrack/problem.py
pyasyncbtrack/solver.py
pyasyncbtrack/types.py
pyasyncbtrack-0.11.0.dist-info/licenses/LICENSE
pyasyncbtrack-0.11.0.dist-info/METADATA
pyasyncbtrack-0.11.0.dist-info/WHEEL
pyasyncbtrack-0.11.0.dist-info/top_level.txt
pyasyncbtrack-0.11.0.dist-info/RECORD
