Metadata-Version: 2.4
Name: pyasyncbtrack
Version: 0.11.0
Summary: Asynchronous Backtracking (ABT) for Distributed CSPs
Author: Pieter Cawood
License: MIT License
Project-URL: Homepage, https://github.com/Pieter-Cawood/PyAsyncBTrack
Project-URL: Source, https://github.com/Pieter-Cawood/PyAsyncBTrack
Project-URL: Issues, https://github.com/Pieter-Cawood/PyAsyncBTrack/issues
Keywords: DCSP,Distributed Constraint Satisfaction,Asynchronous Backtracking,ABT,CSP,Constraint Programming,Arc Consistency,AC-3,Nogoods,Backjumping,Heuristics,MRV,LCV
Classifier: Development Status :: 3 - Alpha
Classifier: Intended Audience :: Science/Research
Classifier: Intended Audience :: Developers
Classifier: License :: OSI Approved :: MIT License
Classifier: Programming Language :: Python :: 3
Classifier: Programming Language :: Python :: 3 :: Only
Classifier: Programming Language :: Python :: 3.10
Classifier: Programming Language :: Python :: 3.11
Classifier: Programming Language :: Python :: 3.12
Classifier: Operating System :: OS Independent
Classifier: Environment :: Console
Classifier: Topic :: Scientific/Engineering :: Artificial Intelligence
Classifier: Topic :: Scientific/Engineering :: Mathematics
Classifier: Topic :: Software Development :: Libraries :: Python Modules
Requires-Python: >=3.10
License-File: LICENSE
Dynamic: license-file
